odoo/addons/account_payment_term_restriction_sale/README.rst
odoo/addons/account_payment_term_restriction_sale/__init__.py
odoo/addons/account_payment_term_restriction_sale/__manifest__.py
odoo/addons/account_payment_term_restriction_sale/i18n/account_payment_term_restriction_sale.pot
odoo/addons/account_payment_term_restriction_sale/models/__init__.py
odoo/addons/account_payment_term_restriction_sale/models/res_partner.py
odoo/addons/account_payment_term_restriction_sale/models/sale_order.py
odoo/addons/account_payment_term_restriction_sale/readme/CONTRIBUTORS.rst
odoo/addons/account_payment_term_restriction_sale/readme/DESCRIPTION.rst
odoo/addons/account_payment_term_restriction_sale/static/description/icon.png
odoo/addons/account_payment_term_restriction_sale/static/description/index.html
odoo/addons/account_payment_term_restriction_sale/tests/__init__.py
odoo/addons/account_payment_term_restriction_sale/tests/test_account_payment_term_restriction_sale.py
odoo13_addon_account_payment_term_restriction_sale-13.0.1.0.1.dev4.dist-info/METADATA
odoo13_addon_account_payment_term_restriction_sale-13.0.1.0.1.dev4.dist-info/WHEEL
odoo13_addon_account_payment_term_restriction_sale-13.0.1.0.1.dev4.dist-info/top_level.txt
odoo13_addon_account_payment_term_restriction_sale-13.0.1.0.1.dev4.dist-info/RECORD
